LICENSE
MANIFEST.in
README.rst
setup.py
filesentry/__init__.py
filesentry/__main__.py
filesentry/filesentry.py
filesentryy.egg-info/PKG-INFO
filesentryy.egg-info/SOURCES.txt
filesentryy.egg-info/dependency_links.txt
filesentryy.egg-info/entry_points.txt
filesentryy.egg-info/requires.txt
filesentryy.egg-info/top_level.txt