Metadata-Version: 1.0
Name: filesentryy
Version: 0.5.0
Summary: Python command line tool to compare two directories.
Home-page: https://github.com/rascati
Author: Michael Rascati
Author-email: rascatimichael@gmail.com
License: UNKNOWN
Platform: UNKNOWN
